kymnasium/__init__.py
kymnasium/agent.py
kymnasium/errors.py
kymnasium/evaluate.py
kymnasium/util.py
kymnasium/alkkagi/__init__.py
kymnasium/alkkagi/env.py
kymnasium/alkkagi/registration.py
kymnasium/alkkagi/remote.py
kymnasium/alkkagi/wrappers.py
kymnasium/alkkagi/assets/bgm.ogg
kymnasium/avoid_blurp/__init__.py
kymnasium/avoid_blurp/env.py
kymnasium/avoid_blurp/registration.py
kymnasium/avoid_blurp/wrappers.py
kymnasium/avoid_blurp/assets/bgm.ogg
kymnasium/avoid_blurp/assets/enemies.png
kymnasium/avoid_blurp/assets/players.png
kymnasium/grid_adventure/__init__.py
kymnasium/grid_adventure/env.py
kymnasium/grid_adventure/registration.py
kymnasium/grid_adventure/wrappers.py
kymnasium/grid_adventure/assets/bgm.ogg
kymnasium/grid_adventure/assets/crossing-26x26-v0.csv
kymnasium/grid_adventure/assets/full-maze-26x26-v0.csv
kymnasium/grid_adventure/assets/full-maze-32x32-v0.csv
kymnasium/grid_survivor/__init__.py
kymnasium/grid_survivor/env.py
kymnasium/grid_survivor/registration.py
kymnasium/grid_survivor/wrappers.py
kymnasium/grid_survivor/assets/bgm.ogg
kymnasium/grid_survivor/assets/rescue-34x34-v0.csv
kymnasium-1.0.8.dist-info/METADATA
kymnasium-1.0.8.dist-info/WHEEL
kymnasium-1.0.8.dist-info/top_level.txt
kymnasium-1.0.8.dist-info/RECORD
