Metadata-Version: 2.4
Name: kymnasium
Version: 1.0.8
Summary: The collection of reinforcement learning environments developed for the Artificial Intelligence course at the Department of Computer Science and Engineering, Kangwon National University.
Author-email: Woohyeok Choi <woohyeok.choi@kangwon.ac.kr>
Maintainer-email: Woohyeok Choi <woohyeok.choi@kangwon.ac.kr>
License-Expression: MIT AND (Apache-2.0 OR BSD-2-Clause)
Project-URL: Homepage, https://knu-p4c-lab.github.io/
Keywords: Environment, Agent, Reinforcement Learning, Gymnasium
Classifier: Programming Language :: Python :: 3
Classifier: Programming Language :: Python :: 3.12
Classifier: Intended Audience :: Science/Research
Classifier: Topic :: Scientific/Engineering :: Artificial Intelligence
Requires-Python: >=3.12
Requires-Dist: gymnasium>=1.2.0
Requires-Dist: pygame>=2.6.1
Requires-Dist: minigrid>=3.0.0
Requires-Dist: numpy>=2.0.2
Requires-Dist: pymunk>=7.1.0
Requires-Dist: rpyc>=6.0.2
